django_json_model_field/__init__.py
django_json_model_field/db/__init__.py
django_json_model_field/db/models/__init__.py
django_json_model_field/db/models/base_json_model_field.py
django_json_model_field/db/models/conditional_json_model_attribute.py
django_json_model_field/db/models/conditional_json_model_field.py
django_json_model_field/db/models/json_model.py
django_json_model_field/db/models/json_model_dict_field.py
django_json_model_field/db/models/json_model_dict_state.py
django_json_model_field/db/models/json_model_field.py
django_json_model_field/db/models/json_model_options.py
django_json_model_field/db/models/json_model_state.py
django_json_model_field/db/models/migration_compat.py
django_json_model_field/db/models/migration_compat_field_mixin.py
django_json_model_field/db/models/migration_helpers.py
django_json_model_field/forms/__init__.py
django_json_model_field/forms/nested_form_field.py
django_json_model_field/forms/nested_model_form_field.py
django_json_model_field/forms/widgets.py
django_json_model_field/migration_helpers.py
django_json_model_field/serialization/__init__.py
django_json_model_field/serialization/constants.py
django_json_model_field/serialization/json_model_decoder.py
django_json_model_field/serialization/json_model_encoder.py
django_json_model_field/serialization/types.py
django_json_model_field/templates/django_json_model_field/forms/widgets/nested_form_input.html
django_json_model_field/util.py
django_json_model_field-1.2.2.dist-info/METADATA
django_json_model_field-1.2.2.dist-info/WHEEL
django_json_model_field-1.2.2.dist-info/RECORD
